{"Barlow Semi Condensed":{"fontFamily":"Barlow Semi Condensed","slug":"kubio-BarlowSemiCondensed-400-latin","name":"Barlow Semi Condensed","unicodeRange":"U+0000-00FF, U+0131, U+0152-0153, U+02BB-02BC, U+02C6, U+02DA, U+02DC, U+0304, U+0308, U+0329, U+2000-206F, U+20AC, U+2122, U+2191, U+2193, U+2212, U+2215, U+FEFF, U+FFFD","fontFace":[{"fontFamily":"Barlow Semi Condensed","fontWeight":"400","fontStyle":"italic","unicodeRange":"U+0000-00FF, U+0131, U+0152-0153, U+02BB-02BC, U+02C6, U+02DA, U+02DC, U+0304, U+0308, U+0329, U+2000-206F, U+20AC, U+2122, U+2191, U+2193, U+2212, U+2215, U+FEFF, U+FFFD","subset":"latin","src":["BarlowSemiCondensed-400italic-latin.woff2"]},{"fontFamily":"Barlow Semi Condensed","fontWeight":"700","fontStyle":"italic","unicodeRange":"U+0000-00FF, U+0131, U+0152-0153, U+02BB-02BC, U+02C6, U+02DA, U+02DC, U+0304, U+0308, U+0329, U+2000-206F, U+20AC, U+2122, U+2191, U+2193, U+2212, U+2215, U+FEFF, U+FFFD","subset":"latin","src":["BarlowSemiCondensed-700italic-latin.woff2"]},{"fontFamily":"Barlow Semi Condensed","fontWeight":"300","fontStyle":"normal","unicodeRange":"U+0000-00FF, U+0131, U+0152-0153, U+02BB-02BC, U+02C6, U+02DA, U+02DC, U+0304, U+0308, U+0329, U+2000-206F, U+20AC, U+2122, U+2191, U+2193, U+2212, U+2215, U+FEFF, U+FFFD","subset":"latin","src":["BarlowSemiCondensed-300normal-latin.woff2"]},{"fontFamily":"Barlow Semi Condensed","fontWeight":"400","fontStyle":"normal","unicodeRange":"U+0000-00FF, U+0131, U+0152-0153, U+02BB-02BC, U+02C6, U+02DA, U+02DC, U+0304, U+0308, U+0329, U+2000-206F, U+20AC, U+2122, U+2191, U+2193, U+2212, U+2215, U+FEFF, U+FFFD","subset":"latin","src":["BarlowSemiCondensed-400normal-latin.woff2"]},{"fontFamily":"Barlow Semi Condensed","fontWeight":"500","fontStyle":"normal","unicodeRange":"U+0000-00FF, U+0131, U+0152-0153, U+02BB-02BC, U+02C6, U+02DA, U+02DC, U+0304, U+0308, U+0329, U+2000-206F, U+20AC, U+2122, U+2191, U+2193, U+2212, U+2215, U+FEFF, U+FFFD","subset":"latin","src":["BarlowSemiCondensed-500normal-latin.woff2"]},{"fontFamily":"Barlow Semi Condensed","fontWeight":"600","fontStyle":"normal","unicodeRange":"U+0000-00FF, U+0131, U+0152-0153, U+02BB-02BC, U+02C6, U+02DA, U+02DC, U+0304, U+0308, U+0329, U+2000-206F, U+20AC, U+2122, U+2191, U+2193, U+2212, U+2215, U+FEFF, U+FFFD","subset":"latin","src":["BarlowSemiCondensed-600normal-latin.woff2"]},{"fontFamily":"Barlow Semi Condensed","fontWeight":"700","fontStyle":"normal","unicodeRange":"U+0000-00FF, U+0131, U+0152-0153, U+02BB-02BC, U+02C6, U+02DA, U+02DC, U+0304, U+0308, U+0329, U+2000-206F, U+20AC, U+2122, U+2191, U+2193, U+2212, U+2215, U+FEFF, U+FFFD","subset":"latin","src":["BarlowSemiCondensed-700normal-latin.woff2"]}]},"Montserrat":{"fontFamily":"Montserrat","slug":"kubio-Montserrat-400-latin","name":"Montserrat","unicodeRange":"U+0000-00FF, U+0131, U+0152-0153, U+02BB-02BC, U+02C6, U+02DA, U+02DC, U+0304, U+0308, U+0329, U+2000-206F, U+20AC, U+2122, U+2191, U+2193, U+2212, U+2215, U+FEFF, U+FFFD","fontFace":[{"fontFamily":"Montserrat","fontWeight":"400","fontStyle":"italic","unicodeRange":"U+0000-00FF, U+0131, U+0152-0153, U+02BB-02BC, U+02C6, U+02DA, U+02DC, U+0304, U+0308, U+0329, U+2000-206F, U+20AC, U+2122, U+2191, U+2193, U+2212, U+2215, U+FEFF, U+FFFD","subset":"latin","src":["Montserrat-400italic-latin.woff2"]},{"fontFamily":"Montserrat","fontWeight":"700","fontStyle":"italic","unicodeRange":"U+0000-00FF, U+0131, U+0152-0153, U+02BB-02BC, U+02C6, U+02DA, U+02DC, U+0304, U+0308, U+0329, U+2000-206F, U+20AC, U+2122, U+2191, U+2193, U+2212, U+2215, U+FEFF, U+FFFD","subset":"latin","src":["Montserrat-700italic-latin.woff2"]},{"fontFamily":"Montserrat","fontWeight":"300","fontStyle":"normal","unicodeRange":"U+0000-00FF, U+0131, U+0152-0153, U+02BB-02BC, U+02C6, U+02DA, U+02DC, U+0304, U+0308, U+0329, U+2000-206F, U+20AC, U+2122, U+2191, U+2193, U+2212, U+2215, U+FEFF, U+FFFD","subset":"latin","src":["Montserrat-300normal-latin.woff2"]},{"fontFamily":"Montserrat","fontWeight":"400","fontStyle":"normal","unicodeRange":"U+0000-00FF, U+0131, U+0152-0153, U+02BB-02BC, U+02C6, U+02DA, U+02DC, U+0304, U+0308, U+0329, U+2000-206F, U+20AC, U+2122, U+2191, U+2193, U+2212, U+2215, U+FEFF, U+FFFD","subset":"latin","src":["Montserrat-400normal-latin.woff2"]},{"fontFamily":"Montserrat","fontWeight":"500","fontStyle":"normal","unicodeRange":"U+0000-00FF, U+0131, U+0152-0153, U+02BB-02BC, U+02C6, U+02DA, U+02DC, U+0304, U+0308, U+0329, U+2000-206F, U+20AC, U+2122, U+2191, U+2193, U+2212, U+2215, U+FEFF, U+FFFD","subset":"latin","src":["Montserrat-500normal-latin.woff2"]},{"fontFamily":"Montserrat","fontWeight":"600","fontStyle":"normal","unicodeRange":"U+0000-00FF, U+0131, U+0152-0153, U+02BB-02BC, U+02C6, U+02DA, U+02DC, U+0304, U+0308, U+0329, U+2000-206F, U+20AC, U+2122, U+2191, U+2193, U+2212, U+2215, U+FEFF, U+FFFD","subset":"latin","src":["Montserrat-600normal-latin.woff2"]},{"fontFamily":"Montserrat","fontWeight":"700","fontStyle":"normal","unicodeRange":"U+0000-00FF, U+0131, U+0152-0153, U+02BB-02BC, U+02C6, U+02DA, U+02DC, U+0304, U+0308, U+0329, U+2000-206F, U+20AC, U+2122, U+2191, U+2193, U+2212, U+2215, U+FEFF, U+FFFD","subset":"latin","src":["Montserrat-700normal-latin.woff2"]}]},"Open Sans":{"fontFamily":"Open Sans","slug":"kubio-OpenSans-400-latin","name":"Open Sans","unicodeRange":"U+0000-00FF, U+0131, U+0152-0153, U+02BB-02BC, U+02C6, U+02DA, U+02DC, U+0304, U+0308, U+0329, U+2000-206F, U+20AC, U+2122, U+2191, U+2193, U+2212, U+2215, U+FEFF, U+FFFD","fontFace":[{"fontFamily":"Open Sans","fontWeight":"400","fontStyle":"italic","unicodeRange":"U+0000-00FF, U+0131, U+0152-0153, U+02BB-02BC, U+02C6, U+02DA, U+02DC, U+0304, U+0308, U+0329, U+2000-206F, U+20AC, U+2122, U+2191, U+2193, U+2212, U+2215, U+FEFF, U+FFFD","subset":"latin","src":["OpenSans-400italic-latin.woff2"]},{"fontFamily":"Open Sans","fontWeight":"700","fontStyle":"italic","unicodeRange":"U+0000-00FF, U+0131, U+0152-0153, U+02BB-02BC, U+02C6, U+02DA, U+02DC, U+0304, U+0308, U+0329, U+2000-206F, U+20AC, U+2122, U+2191, U+2193, U+2212, U+2215, U+FEFF, U+FFFD","subset":"latin","src":["OpenSans-700italic-latin.woff2"]},{"fontFamily":"Open Sans","fontWeight":"300","fontStyle":"normal","unicodeRange":"U+0000-00FF, U+0131, U+0152-0153, U+02BB-02BC, U+02C6, U+02DA, U+02DC, U+0304, U+0308, U+0329, U+2000-206F, U+20AC, U+2122, U+2191, U+2193, U+2212, U+2215, U+FEFF, U+FFFD","subset":"latin","src":["OpenSans-300normal-latin.woff2"]},{"fontFamily":"Open Sans","fontWeight":"400","fontStyle":"normal","unicodeRange":"U+0000-00FF, U+0131, U+0152-0153, U+02BB-02BC, U+02C6, U+02DA, U+02DC, U+0304, U+0308, U+0329, U+2000-206F, U+20AC, U+2122, U+2191, U+2193, U+2212, U+2215, U+FEFF, U+FFFD","subset":"latin","src":["OpenSans-400normal-latin.woff2"]},{"fontFamily":"Open Sans","fontWeight":"500","fontStyle":"normal","unicodeRange":"U+0000-00FF, U+0131, U+0152-0153, U+02BB-02BC, U+02C6, U+02DA, U+02DC, U+0304, U+0308, U+0329, U+2000-206F, U+20AC, U+2122, U+2191, U+2193, U+2212, U+2215, U+FEFF, U+FFFD","subset":"latin","src":["OpenSans-500normal-latin.woff2"]},{"fontFamily":"Open Sans","fontWeight":"700","fontStyle":"normal","unicodeRange":"U+0000-00FF, U+0131, U+0152-0153, U+02BB-02BC, U+02C6, U+02DA, U+02DC, U+0304, U+0308, U+0329, U+2000-206F, U+20AC, U+2122, U+2191, U+2193, U+2212, U+2215, U+FEFF, U+FFFD","subset":"latin","src":["OpenSans-700normal-latin.woff2"]}]}}
